llm4data/__init__.py
llm4data/augmentation/Augmentation.md
llm4data/augmentation/microdata/theme_llm.py
llm4data/configs.py
llm4data/embeddings/__init__.py
llm4data/embeddings/base.py
llm4data/embeddings/docs.py
llm4data/embeddings/indicators.py
llm4data/embeddings/microdata.py
llm4data/index/__init__.py
llm4data/index/qdrant.py
llm4data/llm/indicators/wdi_sql.py
llm4data/llm/microdata/.gitkeep
llm4data/prompts/base.py
llm4data/prompts/context.py
llm4data/prompts/indicators/templates.py
llm4data/prompts/indicators/wdi.py
llm4data/prompts/microdata/.gitkeep
llm4data/prompts/microdata/theme_llm.py
llm4data/prompts/utils.py
llm4data/schema/docs/migrate_wbdocs_metadata.py
llm4data/schema/docs/wbdocs.py
llm4data/schema/indicators/create_wdi_text.py
llm4data/schema/schema2info.py
llm4data/scripts/__init__.py
llm4data/scripts/indexing/create_field_index.py
llm4data/scripts/indexing/docs/docs.py
llm4data/scripts/indexing/docs/load_docs.py
llm4data/scripts/indexing/indicators/indicators.py
llm4data/scripts/indexing/indicators/load_indicators.py
llm4data/sources/indicators/wdi.py
llm4data/sources/microdata/.gitkeep
llm4data/utils/microdata/helpers.py
llm4data/utils/microdata/paths.py
llm4data/utils/microdata/quality.py
llm4data/utils/microdata/scraper.py
llm4data/utils/system/cache.py
llm4data/wdi2name.json
llm4data-0.0.10.dist-info/LICENSE
llm4data-0.0.10.dist-info/METADATA
llm4data-0.0.10.dist-info/WHEEL
llm4data-0.0.10.dist-info/RECORD
