Metadata-Version: 2.1
Name: llm4data
Version: 0.0.10
Summary: LLM4Data is a Python library designed to facilitate the application of large language models (LLMs) and artificial intelligence for development data and knowledge discovery.
Author: Aivin V. Solatorio
Author-email: avsolatorio@gmail.com
Requires-Python: >=3.10,<4.0
Classifier: Programming Language :: Python :: 3
Classifier: Programming Language :: Python :: 3.10
Classifier: Programming Language :: Python :: 3.11
Requires-Dist: fire (>=0.5.0,<0.6.0)
Requires-Dist: instructorembedding (>=1.0.1,<2.0.0)
Requires-Dist: langchain (>=0.1.0,<0.2.0)
Requires-Dist: llm-space (>=0.0.3,<0.0.4)
Requires-Dist: metaschema (==0.0.3)
Requires-Dist: numpy (>=1.24.3,<2.0.0)
Requires-Dist: pandas (>=2.0.1,<3.0.0)
Requires-Dist: psycopg2-binary (>=2.9.6,<3.0.0)
Requires-Dist: pycountry (>=22.3.5,<23.0.0)
Requires-Dist: pymupdf (>=1.22.3,<2.0.0)
Requires-Dist: python-dotenv (>=1.0.0,<2.0.0)
Requires-Dist: qdrant-client (>=1.2.0,<2.0.0) ; python_version >= "3.10" and python_version < "3.12"
Requires-Dist: sentence-transformers (==2.2.2)
Requires-Dist: sqlalchemy (>=2.0.15,<3.0.0)
Requires-Dist: tomli (>=2.0.1,<3.0.0)
